{"train/reward": -0.04, "train/raw_reward": 0.0, "train/done": 0, "train/done_env": 0, "train/is_goal": 0, "train/virtual_done": 0, "train/episode_reward_running": 12.700000323278587, "train/episode_raw_reward_running": 0.0, "train/episode_len_running": 445, "env/timeouts": 0, "env/restarts": 0, "env/port": 17005, "_timestamp": 1768821974.852939, "_runtime": 14386.329303979874, "_step": 752800, "episode/reward": 16.280661530332615, "episode/raw_reward": 0.0, "episode/len": 1500, "episode/index": 136, "train/updated": 1, "train/update_seconds": 106.84325766563416, "train/buffer_len": 6000, "train/step": 750000, "train/global_env_steps": 2250000, "train/update_goal_hits": 0, "train/update_terminals": 0, "train/update_shaper_clip_hits": 20, "train/update_scaler_clip_hits": 0, "train/checkpoint_saved": 1, "_wandb": {"runtime": 14393}}